store/__init__.py
store/admin.py
store/apps.py
store/context_processors.py
store/models.py
store/tests.py
store/urls.py
store/utility.py
store/views.py
store/migrations/0001_initial.py
store/migrations/__init__.py
store/static/store/css/layout.css
store/static/store/css/layout.css.map
store/static/store/js/checkout.js
store/static/store/js/homepage.js
store/static/store/js/layout.js
store/static/store/js/orders.js
store/static/store/js/profile.js
store/templates/store/checkout.html
store/templates/store/homepage.html
store/templates/store/order.html
store/templates/store/orders.html
store/templates/store/product.html
store/templates/store/products.html
store/templates/store/profile.html
store/templates/store/search.html
store/templates/store/handlebars/checkout.html
store/templates/store/handlebars/homepage.html
store/templates/store/handlebars/layout.html
store/templates/store/handlebars/profile.html
store/templates/store/includes/cart_offcanvas.html
store/templates/store/includes/header.html
store/templates/store/includes/orders.html
store/templates/store/includes/pagination.html
store/templates/store/includes/product_filter.html
store/templates/store/includes/products.html
store/templates/store/layout/layout.html
store/templatetags/__init__.py
store/templatetags/store_extras.py
django_ecom_store-0.0.4.dist-info/LICENSE
django_ecom_store-0.0.4.dist-info/METADATA
django_ecom_store-0.0.4.dist-info/WHEEL
django_ecom_store-0.0.4.dist-info/top_level.txt
django_ecom_store-0.0.4.dist-info/RECORD
