Metadata-Version: 2.1
Name: django-ecom-store
Version: 0.0.4
Summary: An E-Commerce store for Django Application
Home-page: https://github.com/parisrvs/django-ecom-store
Author: Parijat Srivastava
Author-email: parisrvs@hotmail.com
Project-URL: Bug Tracker, https://github.com/parisrvs/django-ecom-store
Requires-Python: >=3.8
License-File: LICENSE
Requires-Dist: Django (>=4.0)
Requires-Dist: django-user-login (>=0.3.4)
Requires-Dist: pillow (>=9.2)
